Metadata-Version: 1.1
Name: djckeditor
Version: 0.0.1
Summary: Django run app
Home-page: https://github.com/pmaigutyak/djckeditor
Author: Paul Maigutyak
Author-email: pmaigutyak@gmail.com
License: MIT
Download-URL: https://github.com/pmaigutyak/djckeditor/archive/0.0.1.tar.gz
Platform: UNKNOWN
